{
  "_title": [ "蓝毛今天穿什么？" ],
  "_author": [ "imu" ],
  "_date": [ "2026/6/8" ],
  "_version": [ "1.0.0" ],
  "_updateDate": [ "2026/6/8" ],
  "_brief": [ "豹骰牌堆，按日服进度更新，但我更新不及时。" ],
  "_keys": ["蓝毛今天穿什么？"],
  "蓝毛今天穿什么内部":[
    "[图:data/images/card_121_trained.png]",
    "[图:data/images/card_984_trained.png]",
    "[图:data/images/card_940_trained.png]",
    "[图:data/images/card_900_trained.png]",
    "[图:data/images/card_893_trained.png]",
    "[图:data/images/card_888_normal.png]",
    "[图:data/images/card_869_trained.png]",
    "[图:data/images/card_835_trained.png]",
    "[图:data/images/card_826_normal.png]",
    "[图:data/images/card_761_trained.png]",
    "[图:data/images/card_712_normal.png]",
    "[图:data/images/card_650_trained.png]",
    "[图:data/images/card_633_trained.png]",
    "[图:data/images/card_615_trained.png]",
    "[图:data/images/card_602_trained.png]",
    "[图:data/images/card_594_normal.png]",
    "[图:data/images/card_558_trained.png]",
    "[图:data/images/card_539_normal.png]",
    "[图:data/images/card_521_normal.png]",
    "[图:data/images/card_506_trained.png]",
    "[图:data/images/card_472_trained.png]",
    "[图:data/images/card_436_trained.png]",
    "[图:data/images/card_407_trained.png]",
    "[图:data/images/card_382_trained.png]",
    "[图:data/images/card_379_normal.png]",
    "[图:data/images/card_333_trained.png]",
    "[图:data/images/card_280_trained.png]",
    "[图:data/images/card_272_trained.png]",
    "[图:data/images/card_236_normal.png]",
    "[图:data/images/card_214_trained.png]",
    "[图:data/images/card_140_trained.png]",
    "[图:data/images/card_1240_trained.png]",
    "[图:data/images/card_121_trained.png]",
    "[图:data/images/card_1211_normal.png]",
    "[图:data/images/card_1195_trained.png]",
    "[图:data/images/card_1158_trained.png]",
    "[图:data/images/card_1121_normal.png]",
    "[图:data/images/card_1120_normal.png]",
    "[图:data/images/card_1095_normal.png]",
    "[图:data/images/card_1061_trained.png]",
    "[图:data/images/card_1013_trained.png]"
  ],
  "蓝毛今天穿什么？": [ "咦？这片心愿碎片里的家伙好眼熟……诶？！这不是…「我」吗？！\n{%蓝毛今天穿什么内部}唔哇……这个我也帅气得不得了啊~" ]
}